.gitignore
License.txt
README.md
clean.sh
setup.py
./cloud/__init__.py
./cloud/ec2ssh.py
./commandline/__init__.py
./commandline/hadoop.py
./commandline/hadoop_utils.py
./hadoop1/__init__.py
./hadoop1/bootstrap_hadoop.py
./hadoop1/launcher.py
./hadoop2/__init__.py
./hadoop2/bootstrap_hadoop2.py
./hadoop2/launcher.py
./hadoop2/configs/__init__.py
./hadoop2/configs/default/__init__.py
./hadoop2/configs/gordon_hdfs/__init__.py
./hadoop2/configs/gordon_lustre/__init__.py
./hadoop2/configs/stampede_hdfs/__init__.py
./hadoop2/configs/stampede_lustre/__init__.py
./kafka/__init__.py
./kafka/bootstrap_kafka.py
./kafka/configs/__init__.py
./kafka/configs/default/__init__.py
./pilot_hadoop/__init__.py
./pilot_hadoop/pilot_hadoop_test.py
./spark/__init__.py
./spark/bootstrap_spark.py
.idea/uiDesigner.xml
SAGA_Hadoop.egg-info/PKG-INFO
SAGA_Hadoop.egg-info/SOURCES.txt
SAGA_Hadoop.egg-info/dependency_links.txt
SAGA_Hadoop.egg-info/entry_points.txt
SAGA_Hadoop.egg-info/requires.txt
SAGA_Hadoop.egg-info/top_level.txt
commandline/__init__.py
commandline/__init__.pyc
commandline/hadoop.py
commandline/hadoop.pyc
commandline/hadoop_utils.py
hadoop1/__init__.py
hadoop1/bootstrap_hadoop.py
hadoop1/launcher.py
hadoop2/__init__.py
hadoop2/bootstrap_hadoop2.py
hadoop2/launcher.py
hadoop2/configs/__init__.py
hadoop2/configs/default/__init__.py
hadoop2/configs/default/core-site.xml
hadoop2/configs/default/hdfs-site.xml
hadoop2/configs/default/mapred-site.xml
hadoop2/configs/default/yarn-site.xml
hadoop2/configs/gordon_hdfs/__init__.py
hadoop2/configs/gordon_hdfs/core-site.xml
hadoop2/configs/gordon_hdfs/hdfs-site.xml
hadoop2/configs/gordon_hdfs/mapred-site.xml
hadoop2/configs/gordon_hdfs/yarn-site.xml
hadoop2/configs/gordon_lustre/__init__.py
hadoop2/configs/gordon_lustre/core-site.xml
hadoop2/configs/gordon_lustre/hdfs-site.xml
hadoop2/configs/gordon_lustre/mapred-site.xml
hadoop2/configs/gordon_lustre/yarn-site.xml
hadoop2/configs/stampede_hdfs/__init__.py
hadoop2/configs/stampede_hdfs/core-site.xml
hadoop2/configs/stampede_hdfs/hdfs-site.xml
hadoop2/configs/stampede_hdfs/mapred-site.xml
hadoop2/configs/stampede_hdfs/yarn-site.xml
hadoop2/configs/stampede_lustre/__init__.py
