Metadata-Version: 1.1
Name: SAGA-Hadoop
Version: 0.31.1
Summary: SAGA to launch an Hadoop cluster as a normal batch job on Torque/PBS/SLURM clusters
Home-page: https://github.com/drelu/saga-hadoop
Author: Andre Luckow
Author-email: aluckow@clemson.edu
License: UNKNOWN
Platform: Unix
Platform: Linux
Platform: Mac OS
Classifier: Development Status :: 5 - Production/Stable
Classifier: Programming Language :: Python
Classifier: Environment :: Console
Classifier: Topic :: Utilities
